ezstdf/StdfReader.py
ezstdf/StdfReaderBase.py
ezstdf/__init__.py
ezstdf/atdf_cst.py
ezstdf/parsers.py
ezstdf/stdf_cst.py
ezstdf-0.0.3.dist-info/LICENSE
ezstdf-0.0.3.dist-info/METADATA
ezstdf-0.0.3.dist-info/WHEEL
ezstdf-0.0.3.dist-info/top_level.txt
ezstdf-0.0.3.dist-info/RECORD
